{
  "swagger": "2.0",
  "info": {
    "title": "Service Status API",
    "version": "1.0",
    "contact": {
      "name": "Chad Grant",
      "email": "chad.grant@me.com"
    }
  },
  "schemes": [
    "https",
    "http"
  ],
  "consumes": [
    "application/json"
  ],
  "produces": [
    "application/json"
  ],
  "paths": {
    "/v1/deployments": {
      "get": {
        "operationId": "Get",
        "responses": {
          "200": {
            "description": "A successful response.",
            "schema": {
              "$ref": "#/definitions/DeploymentsPaged"
            }
          }
        },
        "parameters": [
          {
            "name": "page",
            "in": "query",
            "required": false,
            "type": "integer",
            "format": "int32"
          },
          {
            "name": "page_size",
            "in": "query",
            "required": false,
            "type": "integer",
            "format": "int32"
          },
          {
            "name": "environment",
            "in": "query",
            "required": false,
            "type": "string"
          },
          {
            "name": "service",
            "in": "query",
            "required": false,
            "type": "string"
          }
        ],
        "tags": [
          "Deployments"
        ]
      }
    },
    "/v1/environment/{environment}/deployments": {
      "get": {
        "operationId": "GetForEnvironment",
        "responses": {
          "200": {
            "description": "A successful response.",
            "schema": {
              "$ref": "#/definitions/DeploymentsPaged"
            }
          }
        },
        "parameters": [
          {
            "name": "environment",
            "in": "path",
            "required": true,
            "type": "string"
          },
          {
            "name": "page",
            "in": "query",
            "required": false,
            "type": "integer",
            "format": "int32"
          },
          {
            "name": "page_size",
            "in": "query",
            "required": false,
            "type": "integer",
            "format": "int32"
          },
          {
            "name": "service",
            "in": "query",
            "required": false,
            "type": "string"
          }
        ],
        "tags": [
          "Deployments"
        ]
      }
    },
    "/v1/environment/{environment}/service/{service}/deployments": {
      "get": {
        "operationId": "GetForService",
        "responses": {
          "200": {
            "description": "A successful response.",
            "schema": {
              "$ref": "#/definitions/DeploymentsPaged"
            }
          }
        },
        "parameters": [
          {
            "name": "environment",
            "in": "path",
            "required": true,
            "type": "string"
          },
          {
            "name": "service",
            "in": "path",
            "required": true,
            "type": "string"
          },
          {
            "name": "page",
            "in": "query",
            "required": false,
            "type": "integer",
            "format": "int32"
          },
          {
            "name": "page_size",
            "in": "query",
            "required": false,
            "type": "integer",
            "format": "int32"
          }
        ],
        "tags": [
          "Deployments"
        ]
      },
      "post": {
        "operationId": "Add",
        "responses": {
          "200": {
            "description": "A successful response.",
            "schema": {
              "$ref": "#/definitions/Deployment"
            }
          }
        },
        "parameters": [
          {
            "name": "environment",
            "in": "path",
            "required": true,
            "type": "string"
          },
          {
            "name": "service",
            "in": "path",
            "required": true,
            "type": "string"
          },
          {
            "name": "body",
            "in": "body",
            "required": true,
            "schema": {
              "$ref": "#/definitions/Deployment"
            }
          }
        ],
        "tags": [
          "Deployments"
        ]
      }
    },
    "/v1/environment/{key}": {
      "put": {
        "operationId": "Update",
        "responses": {
          "200": {
            "description": "A successful response.",
            "schema": {
              "$ref": "#/definitions/Environment"
            }
          }
        },
        "parameters": [
          {
            "name": "key",
            "in": "path",
            "required": true,
            "type": "string"
          },
          {
            "name": "body",
            "in": "body",
            "required": true,
            "schema": {
              "type": "string"
            }
          }
        ],
        "tags": [
          "Environments"
        ]
      }
    },
    "/v1/environments": {
      "get": {
        "operationId": "Get",
        "responses": {
          "200": {
            "description": "A successful response.",
            "schema": {
              "$ref": "#/definitions/EnvironmentsPaged"
            }
          }
        },
        "tags": [
          "Environments"
        ]
      },
      "post": {
        "operationId": "Add",
        "responses": {
          "200": {
            "description": "A successful response.",
            "schema": {
              "$ref": "#/definitions/Environment"
            }
          }
        },
        "tags": [
          "Environments"
        ]
      }
    },
    "/v1/environments/{environment}/services": {
      "get": {
        "operationId": "GetForEnvironment",
        "responses": {
          "200": {
            "description": "A successful response.",
            "schema": {
              "$ref": "#/definitions/ServicesPaged"
            }
          }
        },
        "parameters": [
          {
            "name": "environment",
            "in": "path",
            "required": true,
            "type": "string"
          },
          {
            "name": "page",
            "in": "query",
            "required": false,
            "type": "integer",
            "format": "int32"
          },
          {
            "name": "page_size",
            "in": "query",
            "required": false,
            "type": "integer",
            "format": "int32"
          }
        ],
        "tags": [
          "Services"
        ]
      }
    },
    "/v1/service/{key}": {
      "put": {
        "operationId": "Update",
        "responses": {
          "200": {
            "description": "A successful response.",
            "schema": {
              "$ref": "#/definitions/Service"
            }
          }
        },
        "parameters": [
          {
            "name": "key",
            "in": "path",
            "required": true,
            "type": "string"
          },
          {
            "name": "body",
            "in": "body",
            "required": true,
            "schema": {
              "type": "string"
            }
          }
        ],
        "tags": [
          "Services"
        ]
      }
    },
    "/v1/services": {
      "get": {
        "operationId": "Get",
        "responses": {
          "200": {
            "description": "A successful response.",
            "schema": {
              "$ref": "#/definitions/ServicesPaged"
            }
          }
        },
        "parameters": [
          {
            "name": "page",
            "in": "query",
            "required": false,
            "type": "integer",
            "format": "int32"
          },
          {
            "name": "page_size",
            "in": "query",
            "required": false,
            "type": "integer",
            "format": "int32"
          },
          {
            "name": "environment",
            "in": "query",
            "required": false,
            "type": "string"
          }
        ],
        "tags": [
          "Services"
        ]
      },
      "post": {
        "operationId": "Add",
        "responses": {
          "200": {
            "description": "A successful response.",
            "schema": {
              "$ref": "#/definitions/Service"
            }
          }
        },
        "parameters": [
          {
            "name": "body",
            "in": "body",
            "required": true,
            "schema": {
              "$ref": "#/definitions/Service"
            }
          }
        ],
        "tags": [
          "Services"
        ]
      }
    }
  },
  "definitions": {
    "Deployment": {
      "type": "object",
      "properties": {
        "id": {
          "type": "string"
        },
        "service": {
          "type": "string"
        },
        "environment": {
          "type": "string"
        },
        "build_number": {
          "type": "string"
        },
        "created": {
          "type": "string",
          "format": "date-time"
        },
        "updated": {
          "type": "string",
          "format": "date-time"
        }
      }
    },
    "DeploymentsPaged": {
      "type": "object",
      "properties": {
        "results": {
          "type": "array",
          "items": {
            "$ref": "#/definitions/Deployment"
          }
        },
        "page": {
          "type": "integer",
          "format": "int32"
        },
        "page_size": {
          "type": "integer",
          "format": "int32"
        },
        "total": {
          "type": "integer",
          "format": "int32"
        },
        "links": {
          "$ref": "#/definitions/Links"
        }
      }
    },
    "Environment": {
      "type": "object",
      "properties": {
        "name": {
          "type": "string"
        },
        "friendly": {
          "type": "string"
        },
        "active": {
          "type": "boolean",
          "format": "boolean"
        },
        "sort": {
          "type": "integer",
          "format": "int32"
        },
        "key": {
          "type": "string"
        },
        "created": {
          "type": "string",
          "format": "date-time"
        },
        "updated": {
          "type": "string",
          "format": "date-time"
        }
      }
    },
    "EnvironmentsPaged": {
      "type": "object",
      "properties": {
        "results": {
          "type": "array",
          "items": {
            "$ref": "#/definitions/Environment"
          }
        }
      }
    },
    "Links": {
      "type": "object",
      "properties": {
        "next": {
          "type": "string"
        },
        "prev": {
          "type": "string"
        }
      }
    },
    "Service": {
      "type": "object",
      "properties": {
        "name": {
          "type": "string"
        },
        "friendly": {
          "type": "string"
        },
        "active": {
          "type": "boolean",
          "format": "boolean"
        },
        "status": {
          "type": "string"
        },
        "sort": {
          "type": "integer",
          "format": "int32"
        },
        "key": {
          "type": "string"
        },
        "created": {
          "type": "string",
          "format": "date-time"
        },
        "updated": {
          "type": "string",
          "format": "date-time"
        }
      }
    },
    "ServicesPaged": {
      "type": "object",
      "properties": {
        "results": {
          "type": "array",
          "items": {
            "$ref": "#/definitions/Service"
          }
        },
        "page": {
          "type": "integer",
          "format": "int32"
        },
        "page_size": {
          "type": "integer",
          "format": "int32"
        },
        "total": {
          "type": "integer",
          "format": "int32"
        },
        "links": {
          "$ref": "#/definitions/Links"
        }
      }
    }
  },
  "externalDocs": {
    "description": "gRPC example repository",
    "url": "https://github.com/gogo/grpc-example"
  }
}
